caddysnake-0.2.2.dist-info/METADATA
caddysnake-0.2.2.dist-info/WHEEL
caddysnake-0.2.2.dist-info/entry_points.txt
caddysnake-cli
caddysnake/__init__.py
caddysnake/caddysnake.cpython-312-aarch64-linux-gnu.so
caddysnake_cli.py
caddysnake-0.2.2.dist-info/RECORD
