Metadata-Version: 2.4
Name: caddysnake
Version: 0.2.2
Classifier: Development Status :: 3 - Alpha
Classifier: Environment :: Console
Classifier: Intended Audience :: Developers
Classifier: License :: OSI Approved :: MIT License
Classifier: Programming Language :: Python :: 3
Classifier: Programming Language :: Python :: 3.10
Classifier: Programming Language :: Python :: 3.11
Classifier: Programming Language :: Python :: 3.12
Classifier: Programming Language :: Python :: 3.13
Classifier: Programming Language :: Go
Requires-Dist: click>=8.3.0
Summary: Python WSGI/ASGI server powered by Caddy
Author-email: Miguel Liezun <liezun.js@gmail.com>
Requires-Python: >=3.10
Project-URL: Homepage, https://caddy-snake.readthedocs.io
Project-URL: Repository, https://github.com/mliezun/caddy-snake.git
